odoo/addons/product_default_code_res_company_code/README.rst
odoo/addons/product_default_code_res_company_code/__init__.py
odoo/addons/product_default_code_res_company_code/__manifest__.py
odoo/addons/product_default_code_res_company_code/post_init_hook.py
odoo/addons/product_default_code_res_company_code/i18n/it.po
odoo/addons/product_default_code_res_company_code/i18n/product_default_code_res_company_code.pot
odoo/addons/product_default_code_res_company_code/models/__init__.py
odoo/addons/product_default_code_res_company_code/models/product_product.py
odoo/addons/product_default_code_res_company_code/models/res_company.py
odoo/addons/product_default_code_res_company_code/readme/CONTRIBUTORS.rst
odoo/addons/product_default_code_res_company_code/readme/DESCRIPTION.rst
odoo/addons/product_default_code_res_company_code/static/description/icon.png
odoo/addons/product_default_code_res_company_code/static/description/index.html
odoo/addons/product_default_code_res_company_code/static/description/product_product_form.png
odoo/addons/product_default_code_res_company_code/static/description/sequence_form.png
odoo/addons/product_default_code_res_company_code/tests/__init__.py
odoo/addons/product_default_code_res_company_code/tests/test_product_default_code.py
odoo/addons/product_default_code_res_company_code/views/view_product_product.xml
odoo/addons/product_default_code_res_company_code/views/view_product_template.xml
odoo_addon_product_default_code_res_company_code-16.0.1.0.0.5.dist-info/METADATA
odoo_addon_product_default_code_res_company_code-16.0.1.0.0.5.dist-info/WHEEL
odoo_addon_product_default_code_res_company_code-16.0.1.0.0.5.dist-info/top_level.txt
odoo_addon_product_default_code_res_company_code-16.0.1.0.0.5.dist-info/RECORD
