Metadata-Version: 2.1
Name: odoo-addon-product_default_code_res_company_code
Version: 16.0.1.0.0.5
Summary: Generate product default code based on sequence defined by company, prefixed by company code
Home-page: https://github.com/OCA/multi-company
Author: GRAP, Odoo Community Association (OCA)
Author-email: support@odoo-community.org
License: AGPL-3
Classifier: Programming Language :: Python
Classifier: Framework :: Odoo
Classifier: Framework :: Odoo :: 16.0
Classifier: License :: OSI Approved :: GNU Affero General Public License v3
Requires-Python: >=3.10
Requires-Dist: odoo-addon-res-company-code<16.1dev,>=16.0dev
Requires-Dist: odoo<16.1dev,>=16.0a
